README.md
setup.py
swarms/__init__.py
swarms/create.py
swarms/create_task_with_image.py
swarms/delete.py
swarms/retrieve.py
swarms/sdk/__init__.py
swarms/sdk/auth.py
swarms/sdk/base_service.py
swarms/sdk/campaigns.py
swarms/sdk/jobs.py
swarms/sdk/results.py
swarms/sdk/services.py
swarms/sdk/tasks.py
swarms/sdk/utils/__init__.py
swarms/sdk/utils/client.py
swarms/sdk/utils/exceptions.py
swarms/sdk/utils/hal.py
swarms_sdk.egg-info/PKG-INFO
swarms_sdk.egg-info/SOURCES.txt
swarms_sdk.egg-info/dependency_links.txt
swarms_sdk.egg-info/requires.txt
swarms_sdk.egg-info/top_level.txt