Metadata-Version: 1.0
Name: swarms-sdk
Version: 0.12
Summary: The Swarms API SDK
Home-page: http://github.com/swarms/python-sdk
Author: Swarms Technologies
Author-email: UNKNOWN
License: MIT
Platform: UNKNOWN
